{
  "swagger": "2.0",
  "info": {
    "title": "wallet.proto",
    "version": "version not set"
  },
  "schemes": [
    "http",
    "https"
  ],
  "consumes": [
    "application/json"
  ],
  "produces": [
    "application/json"
  ],
  "paths": {
    "/api/wallet/balance": {
      "get": {
        "operationId": "GetWalletBalance",
        "responses": {
          "200": {
            "description": "A successful response.",
            "schema": {
              "$ref": "#/definitions/appserver_serves_uiGetWalletBalanceResponse"
            }
          }
        },
        "parameters": [
          {
            "name": "userId",
            "in": "query",
            "required": false,
            "type": "string",
            "format": "int64"
          },
          {
            "name": "orgId",
            "in": "query",
            "required": false,
            "type": "string",
            "format": "int64"
          }
        ],
        "tags": [
          "WalletService"
        ]
      }
    },
    "/api/wallet/{orgId}/downlink_price": {
      "get": {
        "operationId": "GetDlPrice",
        "responses": {
          "200": {
            "description": "A successful response.",
            "schema": {
              "$ref": "#/definitions/appserver_serves_uiGetDownLinkPriceResponse"
            }
          }
        },
        "parameters": [
          {
            "name": "orgId",
            "in": "path",
            "required": true,
            "type": "string",
            "format": "int64"
          }
        ],
        "tags": [
          "WalletService"
        ]
      }
    },
    "/api/wallet/{orgId}/tx-history": {
      "get": {
        "operationId": "GetVmxcTxHistory",
        "responses": {
          "200": {
            "description": "A successful response.",
            "schema": {
              "$ref": "#/definitions/appserver_serves_uiGetVmxcTxHistoryResponse"
            }
          }
        },
        "parameters": [
          {
            "name": "orgId",
            "in": "path",
            "required": true,
            "type": "string",
            "format": "int64"
          },
          {
            "name": "offset",
            "in": "query",
            "required": false,
            "type": "string",
            "format": "int64"
          },
          {
            "name": "limit",
            "in": "query",
            "required": false,
            "type": "string",
            "format": "int64"
          }
        ],
        "tags": [
          "WalletService"
        ]
      }
    },
    "/api/wallet/{orgId}/usage-history": {
      "get": {
        "operationId": "GetWalletUsageHist",
        "responses": {
          "200": {
            "description": "A successful response.",
            "schema": {
              "$ref": "#/definitions/appserver_serves_uiGetWalletUsageHistResponse"
            }
          }
        },
        "parameters": [
          {
            "name": "orgId",
            "in": "path",
            "required": true,
            "type": "string",
            "format": "int64"
          },
          {
            "name": "offset",
            "in": "query",
            "required": false,
            "type": "string",
            "format": "int64"
          },
          {
            "name": "limit",
            "in": "query",
            "required": false,
            "type": "string",
            "format": "int64"
          }
        ],
        "tags": [
          "WalletService"
        ]
      }
    }
  },
  "definitions": {
    "appserver_serves_uiGetDownLinkPriceResponse": {
      "type": "object",
      "properties": {
        "downLinkPrice": {
          "type": "number",
          "format": "double"
        },
        "userProfile": {
          "$ref": "#/definitions/appserver_serves_uiProfileResponse"
        }
      }
    },
    "appserver_serves_uiGetVmxcTxHistoryResponse": {
      "type": "object",
      "properties": {
        "count": {
          "type": "string",
          "format": "int64"
        },
        "txHistory": {
          "type": "array",
          "items": {
            "$ref": "#/definitions/appserver_serves_uiVmxcTxHistory"
          }
        },
        "userProfile": {
          "$ref": "#/definitions/appserver_serves_uiProfileResponse"
        }
      }
    },
    "appserver_serves_uiGetWalletBalanceResponse": {
      "type": "object",
      "properties": {
        "balance": {
          "type": "number",
          "format": "double"
        },
        "userProfile": {
          "$ref": "#/definitions/m2m_uiProfileResponse"
        }
      }
    },
    "appserver_serves_uiGetWalletUsageHist": {
      "type": "object",
      "properties": {
        "StartAt": {
          "type": "string"
        },
        "DurationMinutes": {
          "type": "string",
          "format": "int64"
        },
        "DlCntDv": {
          "type": "string",
          "format": "int64"
        },
        "DlCntDvFree": {
          "type": "string",
          "format": "int64"
        },
        "UlCntDv": {
          "type": "string",
          "format": "int64"
        },
        "UlCntDvFree": {
          "type": "string",
          "format": "int64"
        },
        "DlCntGw": {
          "type": "string",
          "format": "int64"
        },
        "DlCntGwFree": {
          "type": "string",
          "format": "int64"
        },
        "UlCntGw": {
          "type": "string",
          "format": "int64"
        },
        "UlCntGwFree": {
          "type": "string",
          "format": "int64"
        },
        "Spend": {
          "type": "number",
          "format": "double"
        },
        "Income": {
          "type": "number",
          "format": "double"
        },
        "UpdatedBalance": {
          "type": "number",
          "format": "double"
        }
      }
    },
    "appserver_serves_uiGetWalletUsageHistResponse": {
      "type": "object",
      "properties": {
        "walletUsageHis": {
          "type": "array",
          "items": {
            "$ref": "#/definitions/appserver_serves_uiGetWalletUsageHist"
          }
        },
        "userProfile": {
          "$ref": "#/definitions/appserver_serves_uiProfileResponse"
        },
        "count": {
          "type": "string",
          "format": "int64"
        }
      }
    },
    "appserver_serves_uiOrganizationLink": {
      "type": "object",
      "properties": {
        "organizationID": {
          "type": "string",
          "format": "int64",
          "description": "Organization ID."
        },
        "organizationName": {
          "type": "string",
          "description": "Organization name."
        },
        "isAdmin": {
          "type": "boolean",
          "format": "boolean",
          "description": "User is admin within the context of this organization.\nThere is no need to set the is_device_admin and is_gateway_admin flags."
        },
        "isDeviceAdmin": {
          "type": "boolean",
          "format": "boolean",
          "description": "User is able to modify device related resources (applications,\ndevice-profiles, devices, multicast-groups)."
        },
        "isGatewayAdmin": {
          "type": "boolean",
          "format": "boolean",
          "description": "User is able to modify gateways."
        },
        "createdAt": {
          "type": "string",
          "format": "date-time",
          "description": "Created at timestamp."
        },
        "updatedAt": {
          "type": "string",
          "format": "date-time",
          "description": "Last update timestamp."
        }
      },
      "description": "Defines an organization to which an user is associated."
    },
    "appserver_serves_uiProfileResponse": {
      "type": "object",
      "properties": {
        "user": {
          "$ref": "#/definitions/appserver_serves_uiUser",
          "description": "User object."
        },
        "organizations": {
          "type": "array",
          "items": {
            "$ref": "#/definitions/appserver_serves_uiOrganizationLink"
          },
          "description": "Organizations to which the user is associated."
        },
        "settings": {
          "$ref": "#/definitions/appserver_serves_uiProfileSettings",
          "description": "Profile settings."
        }
      }
    },
    "appserver_serves_uiProfileSettings": {
      "type": "object",
      "properties": {
        "disableAssignExistingUsers": {
          "type": "boolean",
          "format": "boolean",
          "description": "Existing users in the system can not be assigned to organizations and\napplication and can not be listed by non global admin users."
        }
      }
    },
    "appserver_serves_uiUser": {
      "type": "object",
      "properties": {
        "id": {
          "type": "string",
          "format": "int64",
          "description": "User ID.\nWill be set automatically on create."
        },
        "username": {
          "type": "string",
          "description": "Username of the user."
        },
        "sessionTTL": {
          "type": "integer",
          "format": "int32",
          "description": "The session timeout, in minutes."
        },
        "isAdmin": {
          "type": "boolean",
          "format": "boolean",
          "description": "Set to true to make the user a global administrator."
        },
        "isActive": {
          "type": "boolean",
          "format": "boolean",
          "description": "Set to false to disable the user."
        },
        "email": {
          "type": "string",
          "description": "E-mail of the user."
        },
        "note": {
          "type": "string",
          "description": "Optional note to store with the user."
        }
      }
    },
    "appserver_serves_uiVmxcTxHistory": {
      "type": "object",
      "properties": {
        "from": {
          "type": "string"
        },
        "to": {
          "type": "string"
        },
        "txType": {
          "type": "string"
        },
        "amount": {
          "type": "number",
          "format": "double"
        },
        "createdAt": {
          "type": "string"
        }
      }
    }
  }
}
